{"label_size": 14, "top_path": "../../../../../data/gern/egg_human/original", "anim_count": 651, "labels": {"bt": {"target": "L00", "data": {"rigs": {"/woman1/woman12bt.egg": {"target": "L00.R0004.egg", "data": {"anim_count": 9, "animations": {"/woman1/woman12bt-bt4.egg": {"target": "L00.R0004.A0001.egg"}, "/woman1/woman12bt-bt2.egg": {"target": "L00.R0004.A0002.egg"}, "/woman1/woman12bt-bt3.egg": {"target": "L00.R0004.A0005.egg"}, "/woman1/woman12bt-bt7.egg": {"target": "L00.R0004.A0004.egg"}, "/woman1/woman12bt-bt6.egg": {"target": "L00.R0004.A0008.egg"}, "/woman1/woman12bt-bt5.egg": {"target": "L00.R0004.A0000.egg"}, "/woman1/woman12bt-bt9.egg": {"target": "L00.R0004.A0007.egg"}, "/woman1/woman12bt-bt10.egg": {"target": "L00.R0004.A0006.egg"}, "/woman1/woman12bt-bt8.egg": {"target": "L00.R0004.A0003.egg"}}, "animation_size": 9}}, "/man0/man0bt.egg": {"target": "L00.R0006.egg", "data": {"anim_count": 10, "animations": {"/man0/man0bt-bt8.egg": {"target": "L00.R0006.A0000.egg"}, "/man0/man0bt-bt6.egg": {"target": "L00.R0006.A0007.egg"}, "/man0/man0bt-bt9.egg": {"target": "L00.R0006.A0002.egg"}, "/man0/man0bt-bt10.egg": {"target": "L00.R0006.A0004.egg"}, "/man0/man0bt-bt4.egg": {"target": "L00.R0006.A0001.egg"}, "/man0/man0bt-bt5.egg": {"target": "L00.R0006.A0005.egg"}, "/man0/man0bt-bt1.egg": {"target": "L00.R0006.A0008.egg"}, "/man0/man0bt-bt2.egg": {"target": "L00.R0006.A0009.egg"}, "/man0/man0bt-bt3.egg": {"target": "L00.R0006.A0006.egg"}, "/man0/man0bt-bt7.egg": {"target": "L00.R0006.A0003.egg"}}, "animation_size": 10}}, "/woman1/woman1bt.egg": {"target": "L00.R0005.egg", "data": {"anim_count": 1, "animations": {"/woman1/woman1bt-bt.egg": {"target": "L00.R0005.A0000.egg"}}, "animation_size": 1}}, "/woman2/woman2bt.egg": {"target": "L00.R0000.egg", "data": {"anim_count": 1, "animations": {"/woman2/woman2bt-bt.egg": {"target": "L00.R0000.A0000.egg"}}, "animation_size": 1}}, "/woman2/women22bt.egg": {"target": "L00.R0001.egg", "data": {"anim_count": 9, "animations": {"/woman2/women22bt-bt5.egg": {"target": "L00.R0001.A0006.egg"}, "/woman2/women22bt-bt9.egg": {"target": "L00.R0001.A0008.egg"}, "/woman2/women22bt-bt8.egg": {"target": "L00.R0001.A0002.egg"}, "/woman2/women22bt-bt4.egg": {"target": "L00.R0001.A0001.egg"}, "/woman2/women22bt-bt10.egg": {"target": "L00.R0001.A0003.egg"}, "/woman2/women22bt-bt2.egg": {"target": "L00.R0001.A0005.egg"}, "/woman2/women22bt-bt6.egg": {"target": "L00.R0001.A0004.egg"}, "/woman2/women22bt-bt3.egg": {"target": "L00.R0001.A0000.egg"}, "/woman2/women22bt-bt7.egg": {"target": "L00.R0001.A0007.egg"}}, "animation_size": 9}}, "/man1/man1bt.egg": {"target": "L00.R0003.egg", "data": {"anim_count": 1, "animations": {"/man1/man1bt-bt.egg": {"target": "L00.R0003.A0000.egg"}}, "animation_size": 1}}, "/man1/man12bt.egg": {"target": "L00.R0002.egg", "data": {"anim_count": 9, "animations": {"/man1/man12bt-bt6.egg": {"target": "L00.R0002.A0000.egg"}, "/man1/man12bt-bt5.egg": {"target": "L00.R0002.A0001.egg"}, "/man1/man12bt-bt10.egg": {"target": "L00.R0002.A0006.egg"}, "/man1/man12bt-bt7.egg": {"target": "L00.R0002.A0005.egg"}, "/man1/man12bt-bt3.egg": {"target": "L00.R0002.A0003.egg"}, "/man1/man12bt-bt9.egg": {"target": "L00.R0002.A0004.egg"}, "/man1/man12bt-bt8.egg": {"target": "L00.R0002.A0008.egg"}, "/man1/man12bt-bt2.egg": {"target": "L00.R0002.A0007.egg"}, "/man1/man12bt-bt4.egg": {"target": "L00.R0002.A0002.egg"}}, "animation_size": 9}}, "/man2/man22bt.egg": {"target": "L00.R0007.egg", "data": {"anim_count": 9, "animations": {"/man2/man22bt-bt5.egg": {"target": "L00.R0007.A0001.egg"}, "/man2/man22bt-bt9.egg": {"target": "L00.R0007.A0005.egg"}, "/man2/man22bt-bt7.egg": {"target": "L00.R0007.A0004.egg"}, "/man2/man22bt-bt10.egg": {"target": "L00.R0007.A0006.egg"}, "/man2/man22bt-bt3.egg": {"target": "L00.R0007.A0003.egg"}, "/man2/man22bt-bt2.egg": {"target": "L00.R0007.A0007.egg"}, "/man2/man22bt-bt8.egg": {"target": "L00.R0007.A0008.egg"}, "/man2/man22bt-bt4.egg": {"target": "L00.R0007.A0002.egg"}, "/man2/man22bt-bt6.egg": {"target": "L00.R0007.A0000.egg"}}, "animation_size": 9}}, "/man2/man2bt.egg": {"target": "L00.R0008.egg", "data": {"anim_count": 1, "animations": {"/man2/man2bt-bt.egg": {"target": "L00.R0008.A0000.egg"}}, "animation_size": 1}}}, "anim_count": 50, "rig_count": 9, "rig_size": 9}}, "mt1": {"target": "L03", "data": {"rigs": {"/man1/man12mt1.egg": {"target": "L03.R0003.egg", "data": {"anim_count": 9, "animations": {"/man1/man12mt1-mt14.egg": {"target": "L03.R0003.A0005.egg"}, "/man1/man12mt1-mt18.egg": {"target": "L03.R0003.A0004.egg"}, "/man1/man12mt1-mt15.egg": {"target": "L03.R0003.A0001.egg"}, "/man1/man12mt1-mt13.egg": {"target": "L03.R0003.A0002.egg"}, "/man1/man12mt1-mt12.egg": {"target": "L03.R0003.A0006.egg"}, "/man1/man12mt1-mt17.egg": {"target": "L03.R0003.A0007.egg"}, "/man1/man12mt1-mt110.egg": {"target": "L03.R0003.A0003.egg"}, "/man1/man12mt1-mt19.egg": {"target": "L03.R0003.A0008.egg"}, "/man1/man12mt1-mt16.egg": {"target": "L03.R0003.A0000.egg"}}, "animation_size": 9}}, "/woman2/women22mt1.egg": {"target": "L03.R0000.egg", "data": {"anim_count": 9, "animations": {"/woman2/women22mt1-mt16.egg": {"target": "L03.R0000.A0002.egg"}, "/woman2/women22mt1-mt14.egg": {"target": "L03.R0000.A0001.egg"}, "/woman2/women22mt1-mt12.egg": {"target": "L03.R0000.A0006.egg"}, "/woman2/women22mt1-mt110.egg": {"target": "L03.R0000.A0000.egg"}, "/woman2/women22mt1-mt13.egg": {"target": "L03.R0000.A0005.egg"}, "/woman2/women22mt1-mt15.egg": {"target": "L03.R0000.A0007.egg"}, "/woman2/women22mt1-mt18.egg": {"target": "L03.R0000.A0008.egg"}, "/woman2/women22mt1-mt17.egg": {"target": "L03.R0000.A0004.egg"}, "/woman2/women22mt1-mt19.egg": {"target": "L03.R0000.A0003.egg"}}, "animation_size": 9}}, "/man1/man1mt1.egg": {"target": "L03.R0002.egg", "data": {"anim_count": 1, "animations": {"/man1/man1mt1-mt1.egg": {"target": "L03.R0002.A0000.egg"}}, "animation_size": 1}}, "/man2/man2mt1.egg": {"target": "L03.R0008.egg", "data": {"anim_count": 1, "animations": {"/man2/man2mt1-mt1.egg": {"target": "L03.R0008.A0000.egg"}}, "animation_size": 1}}, "/woman1/woman1mt1.egg": {"target": "L03.R0005.egg", "data": {"anim_count": 1, "animations": {"/woman1/woman1mt1-mt1.egg": {"target": "L03.R0005.A0000.egg"}}, "animation_size": 1}}, "/man0/man0mt1.egg": {"target": "L03.R0006.egg", "data": {"anim_count": 10, "animations": {"/man0/man0mt1-mt12.egg": {"target": "L03.R0006.A0009.egg"}, "/man0/man0mt1-mt17.egg": {"target": "L03.R0006.A0000.egg"}, "/man0/man0mt1-mt15.egg": {"target": "L03.R0006.A0007.egg"}, "/man0/man0mt1-mt14.egg": {"target": "L03.R0006.A0006.egg"}, "/man0/man0mt1-mt16.egg": {"target": "L03.R0006.A0001.egg"}, "/man0/man0mt1-mt19.egg": {"target": "L03.R0006.A0004.egg"}, "/man0/man0mt1-mt13.egg": {"target": "L03.R0006.A0003.egg"}, "/man0/man0mt1-mt11.egg": {"target": "L03.R0006.A0008.egg"}, "/man0/man0mt1-mt110.egg": {"target": "L03.R0006.A0005.egg"}, "/man0/man0mt1-mt18.egg": {"target": "L03.R0006.A0002.egg"}}, "animation_size": 10}}, "/man2/man22mt1.egg": {"target": "L03.R0007.egg", "data": {"anim_count": 9, "animations": {"/man2/man22mt1-mt13.egg": {"target": "L03.R0007.A0000.egg"}, "/man2/man22mt1-mt110.egg": {"target": "L03.R0007.A0007.egg"}, "/man2/man22mt1-mt14.egg": {"target": "L03.R0007.A0001.egg"}, "/man2/man22mt1-mt19.egg": {"target": "L03.R0007.A0006.egg"}, "/man2/man22mt1-mt18.egg": {"target": "L03.R0007.A0004.egg"}, "/man2/man22mt1-mt12.egg": {"target": "L03.R0007.A0003.egg"}, "/man2/man22mt1-mt17.egg": {"target": "L03.R0007.A0005.egg"}, "/man2/man22mt1-mt16.egg": {"target": "L03.R0007.A0008.egg"}, "/man2/man22mt1-mt15.egg": {"target": "L03.R0007.A0002.egg"}}, "animation_size": 9}}, "/woman2/woman2mt1.egg": {"target": "L03.R0001.egg", "data": {"anim_count": 1, "animations": {"/woman2/woman2mt1-mt1.egg": {"target": "L03.R0001.A0000.egg"}}, "animation_size": 1}}, "/woman1/woman12mt1.egg": {"target": "L03.R0004.egg", "data": {"anim_count": 9, "animations": {"/woman1/woman12mt1-mt18.egg": {"target": "L03.R0004.A0001.egg"}, "/woman1/woman12mt1-mt110.egg": {"target": "L03.R0004.A0007.egg"}, "/woman1/woman12mt1-mt12.egg": {"target": "L03.R0004.A0003.egg"}, "/woman1/woman12mt1-mt14.egg": {"target": "L03.R0004.A0002.egg"}, "/woman1/woman12mt1-mt17.egg": {"target": "L03.R0004.A0000.egg"}, "/woman1/woman12mt1-mt19.egg": {"target": "L03.R0004.A0006.egg"}, "/woman1/woman12mt1-mt16.egg": {"target": "L03.R0004.A0008.egg"}, "/woman1/woman12mt1-mt13.egg": {"target": "L03.R0004.A0005.egg"}, "/woman1/woman12mt1-mt15.egg": {"target": "L03.R0004.A0004.egg"}}, "animation_size": 9}}}, "anim_count": 50, "rig_count": 9, "rig_size": 9}}, "rb": {"target": "L07", "data": {"rigs": {"/man2/man22rb.egg": {"target": "L07.R0007.egg", "data": {"anim_count": 9, "animations": {"/man2/man22rb-rb2.egg": {"target": "L07.R0007.A0002.egg"}, "/man2/man22rb-rb7.egg": {"target": "L07.R0007.A0006.egg"}, "/man2/man22rb-rb5.egg": {"target": "L07.R0007.A0001.egg"}, "/man2/man22rb-rb10.egg": {"target": "L07.R0007.A0000.egg"}, "/man2/man22rb-rb6.egg": {"target": "L07.R0007.A0008.egg"}, "/man2/man22rb-rb3.egg": {"target": "L07.R0007.A0007.egg"}, "/man2/man22rb-rb4.egg": {"target": "L07.R0007.A0003.egg"}, "/man2/man22rb-rb8.egg": {"target": "L07.R0007.A0004.egg"}, "/man2/man22rb-rb9.egg": {"target": "L07.R0007.A0005.egg"}}, "animation_size": 9}}, "/woman1/woman1rb.egg": {"target": "L07.R0005.egg", "data": {"anim_count": 1, "animations": {"/woman1/woman1rb-rb.egg": {"target": "L07.R0005.A0000.egg"}}, "animation_size": 1}}, "/man0/man0rb.egg": {"target": "L07.R0006.egg", "data": {"anim_count": 10, "animations": {"/man0/man0rb-rb8.egg": {"target": "L07.R0006.A0006.egg"}, "/man0/man0rb-rb5.egg": {"target": "L07.R0006.A0003.egg"}, "/man0/man0rb-rb7.egg": {"target": "L07.R0006.A0008.egg"}, "/man0/man0rb-rb1.egg": {"target": "L07.R0006.A0007.egg"}, "/man0/man0rb-rb4.egg": {"target": "L07.R0006.A0009.egg"}, "/man0/man0rb-rb2.egg": {"target": "L07.R0006.A0001.egg"}, "/man0/man0rb-rb6.egg": {"target": "L07.R0006.A0004.egg"}, "/man0/man0rb-rb3.egg": {"target": "L07.R0006.A0000.egg"}, "/man0/man0rb-rb9.egg": {"target": "L07.R0006.A0002.egg"}, "/man0/man0rb-rb10.egg": {"target": "L07.R0006.A0005.egg"}}, "animation_size": 10}}, "/man2/man2rb.egg": {"target": "L07.R0008.egg", "data": {"anim_count": 1, "animations": {"/man2/man2rb-rb.egg": {"target": "L07.R0008.A0000.egg"}}, "animation_size": 1}}, "/man1/man12rb.egg": {"target": "L07.R0002.egg", "data": {"anim_count": 9, "animations": {"/man1/man12rb-rb2.egg": {"target": "L07.R0002.A0005.egg"}, "/man1/man12rb-rb7.egg": {"target": "L07.R0002.A0006.egg"}, "/man1/man12rb-rb4.egg": {"target": "L07.R0002.A0002.egg"}, "/man1/man12rb-rb8.egg": {"target": "L07.R0002.A0003.egg"}, "/man1/man12rb-rb9.egg": {"target": "L07.R0002.A0004.egg"}, "/man1/man12rb-rb10.egg": {"target": "L07.R0002.A0000.egg"}, "/man1/man12rb-rb3.egg": {"target": "L07.R0002.A0008.egg"}, "/man1/man12rb-rb5.egg": {"target": "L07.R0002.A0007.egg"}, "/man1/man12rb-rb6.egg": {"target": "L07.R0002.A0001.egg"}}, "animation_size": 9}}, "/woman2/woman2rb.egg": {"target": "L07.R0001.egg", "data": {"anim_count": 1, "animations": {"/woman2/woman2rb-rb.egg": {"target": "L07.R0001.A0000.egg"}}, "animation_size": 1}}, "/woman1/woman12rb.egg": {"target": "L07.R0004.egg", "data": {"anim_count": 9, "animations": {"/woman1/woman12rb-rb9.egg": {"target": "L07.R0004.A0000.egg"}, "/woman1/woman12rb-rb8.egg": {"target": "L07.R0004.A0003.egg"}, "/woman1/woman12rb-rb5.egg": {"target": "L07.R0004.A0002.egg"}, "/woman1/woman12rb-rb7.egg": {"target": "L07.R0004.A0005.egg"}, "/woman1/woman12rb-rb10.egg": {"target": "L07.R0004.A0001.egg"}, "/woman1/woman12rb-rb2.egg": {"target": "L07.R0004.A0008.egg"}, "/woman1/woman12rb-rb6.egg": {"target": "L07.R0004.A0006.egg"}, "/woman1/woman12rb-rb3.egg": {"target": "L07.R0004.A0007.egg"}, "/woman1/woman12rb-rb4.egg": {"target": "L07.R0004.A0004.egg"}}, "animation_size": 9}}, "/woman2/women22rb.egg": {"target": "L07.R0000.egg", "data": {"anim_count": 9, "animations": {"/woman2/women22rb-rb8.egg": {"target": "L07.R0000.A0004.egg"}, "/woman2/women22rb-rb9.egg": {"target": "L07.R0000.A0001.egg"}, "/woman2/women22rb-rb2.egg": {"target": "L07.R0000.A0000.egg"}, "/woman2/women22rb-rb5.egg": {"target": "L07.R0000.A0005.egg"}, "/woman2/women22rb-rb6.egg": {"target": "L07.R0000.A0003.egg"}, "/woman2/women22rb-rb4.egg": {"target": "L07.R0000.A0006.egg"}, "/woman2/women22rb-rb3.egg": {"target": "L07.R0000.A0008.egg"}, "/woman2/women22rb-rb7.egg": {"target": "L07.R0000.A0002.egg"}, "/woman2/women22rb-rb10.egg": {"target": "L07.R0000.A0007.egg"}}, "animation_size": 9}}, "/man1/man1rb.egg": {"target": "L07.R0003.egg", "data": {"anim_count": 1, "animations": {"/man1/man1rb-rb.egg": {"target": "L07.R0003.A0000.egg"}}, "animation_size": 1}}}, "anim_count": 50, "rig_count": 9, "rig_size": 9}}, "em": {"target": "L01", "data": {"rigs": {"/man2/man2em.egg": {"target": "L01.R0008.egg", "data": {"anim_count": 1, "animations": {"/man2/man2em-em.egg": {"target": "L01.R0008.A0000.egg"}}, "animation_size": 1}}, "/man2/man22em.egg": {"target": "L01.R0007.egg", "data": {"anim_count": 9, "animations": {"/man2/man22em-em7.egg": {"target": "L01.R0007.A0003.egg"}, "/man2/man22em-em8.egg": {"target": "L01.R0007.A0005.egg"}, "/man2/man22em-em2.egg": {"target": "L01.R0007.A0007.egg"}, "/man2/man22em-em6.egg": {"target": "L01.R0007.A0004.egg"}, "/man2/man22em-em4.egg": {"target": "L01.R0007.A0002.egg"}, "/man2/man22em-em9.egg": {"target": "L01.R0007.A0006.egg"}, "/man2/man22em-em5.egg": {"target": "L01.R0007.A0001.egg"}, "/man2/man22em-em10.egg": {"target": "L01.R0007.A0000.egg"}, "/man2/man22em-em3.egg": {"target": "L01.R0007.A0008.egg"}}, "animation_size": 9}}, "/woman2/woman2em.egg": {"target": "L01.R0000.egg", "data": {"anim_count": 1, "animations": {"/woman2/woman2em-em.egg": {"target": "L01.R0000.A0000.egg"}}, "animation_size": 1}}, "/man1/man1em2.egg": {"target": "L01.R0003.egg", "data": {"anim_count": 1, "animations": {"/man1/man1em2-em2.egg": {"target": "L01.R0003.A0000.egg"}}, "animation_size": 1}}, "/man0/man0em.egg": {"target": "L01.R0006.egg", "data": {"anim_count": 10, "animations": {"/man0/man0em-em5.egg": {"target": "L01.R0006.A0005.egg"}, "/man0/man0em-em3.egg": {"target": "L01.R0006.A0009.egg"}, "/man0/man0em-em4.egg": {"target": "L01.R0006.A0002.egg"}, "/man0/man0em-em1.egg": {"target": "L01.R0006.A0003.egg"}, "/man0/man0em-em2.egg": {"target": "L01.R0006.A0000.egg"}, "/man0/man0em-em6.egg": {"target": "L01.R0006.A0001.egg"}, "/man0/man0em-em9.egg": {"target": "L01.R0006.A0006.egg"}, "/man0/man0em-em10.egg": {"target": "L01.R0006.A0007.egg"}, "/man0/man0em-em7.egg": {"target": "L01.R0006.A0008.egg"}, "/man0/man0em-em8.egg": {"target": "L01.R0006.A0004.egg"}}, "animation_size": 10}}, "/woman2/women22em.egg": {"target": "L01.R0001.egg", "data": {"anim_count": 9, "animations": {"/woman2/women22em-em7.egg": {"target": "L01.R0001.A0004.egg"}, "/woman2/women22em-em6.egg": {"target": "L01.R0001.A0006.egg"}, "/woman2/women22em-em5.egg": {"target": "L01.R0001.A0000.egg"}, "/woman2/women22em-em3.egg": {"target": "L01.R0001.A0002.egg"}, "/woman2/women22em-em4.egg": {"target": "L01.R0001.A0007.egg"}, "/woman2/women22em-em2.egg": {"target": "L01.R0001.A0003.egg"}, "/woman2/women22em-em10.egg": {"target": "L01.R0001.A0001.egg"}, "/woman2/women22em-em8.egg": {"target": "L01.R0001.A0005.egg"}, "/woman2/women22em-em9.egg": {"target": "L01.R0001.A0008.egg"}}, "animation_size": 9}}, "/man1/man12em.egg": {"target": "L01.R0002.egg", "data": {"anim_count": 9, "animations": {"/man1/man12em-em6.egg": {"target": "L01.R0002.A0000.egg"}, "/man1/man12em-em4.egg": {"target": "L01.R0002.A0004.egg"}, "/man1/man12em-em3.egg": {"target": "L01.R0002.A0003.egg"}, "/man1/man12em-em10.egg": {"target": "L01.R0002.A0008.egg"}, "/man1/man12em-em7.egg": {"target": "L01.R0002.A0006.egg"}, "/man1/man12em-em2.egg": {"target": "L01.R0002.A0007.egg"}, "/man1/man12em-em9.egg": {"target": "L01.R0002.A0002.egg"}, "/man1/man12em-em5.egg": {"target": "L01.R0002.A0001.egg"}, "/man1/man12em-em8.egg": {"target": "L01.R0002.A0005.egg"}}, "animation_size": 9}}, "/woman1/woman1em.egg": {"target": "L01.R0005.egg", "data": {"anim_count": 1, "animations": {"/woman1/woman1em-em.egg": {"target": "L01.R0005.A0000.egg"}}, "animation_size": 1}}, "/woman1/woman12em.egg": {"target": "L01.R0004.egg", "data": {"anim_count": 9, "animations": {"/woman1/woman12em-em8.egg": {"target": "L01.R0004.A0007.egg"}, "/woman1/woman12em-em10.egg": {"target": "L01.R0004.A0006.egg"}, "/woman1/woman12em-em6.egg": {"target": "L01.R0004.A0008.egg"}, "/woman1/woman12em-em9.egg": {"target": "L01.R0004.A0004.egg"}, "/woman1/woman12em-em5.egg": {"target": "L01.R0004.A0001.egg"}, "/woman1/woman12em-em3.egg": {"target": "L01.R0004.A0000.egg"}, "/woman1/woman12em-em7.egg": {"target": "L01.R0004.A0005.egg"}, "/woman1/woman12em-em2.egg": {"target": "L01.R0004.A0002.egg"}, "/woman1/woman12em-em4.egg": {"target": "L01.R0004.A0003.egg"}}, "animation_size": 9}}}, "anim_count": 50, "rig_count": 9, "rig_size": 9}}, "wf": {"target": "L11", "data": {"rigs": {"/woman2/woman2.egg": {"target": "L11.R0001.egg", "data": {"anim_count": 1, "animations": {"/woman2/woman2-wf.egg": {"target": "L11.R0001.A0000.egg"}}, "animation_size": 1}}, "/woman1/woman1.egg": {"target": "L11.R0005.egg", "data": {"anim_count": 1, "animations": {"/woman1/woman1-wf.egg": {"target": "L11.R0005.A0000.egg"}}, "animation_size": 1}}, "/man1/man1.egg": {"target": "L11.R0002.egg", "data": {"anim_count": 1, "animations": {"/man1/man1-wf.egg": {"target": "L11.R0002.A0000.egg"}}, "animation_size": 1}}, "/man2/man22.egg": {"target": "L11.R0007.egg", "data": {"anim_count": 9, "animations": {"/man2/man22-wf4.egg": {"target": "L11.R0007.A0000.egg"}, "/man2/man22-wf9.egg": {"target": "L11.R0007.A0004.egg"}, "/man2/man22-wf5.egg": {"target": "L11.R0007.A0006.egg"}, "/man2/man22-wf6.egg": {"target": "L11.R0007.A0003.egg"}, "/man2/man22-wf2.egg": {"target": "L11.R0007.A0007.egg"}, "/man2/man22-wf3.egg": {"target": "L11.R0007.A0002.egg"}, "/man2/man22-wf7.egg": {"target": "L11.R0007.A0001.egg"}, "/man2/man22-wf8.egg": {"target": "L11.R0007.A0005.egg"}, "/man2/man22-wf10.egg": {"target": "L11.R0007.A0008.egg"}}, "animation_size": 9}}, "/man2/man2.egg": {"target": "L11.R0008.egg", "data": {"anim_count": 1, "animations": {"/man2/man2-wf.egg": {"target": "L11.R0008.A0000.egg"}}, "animation_size": 1}}, "/man1/man12.egg": {"target": "L11.R0003.egg", "data": {"anim_count": 9, "animations": {"/man1/man12-wf8.egg": {"target": "L11.R0003.A0003.egg"}, "/man1/man12-wf5.egg": {"target": "L11.R0003.A0000.egg"}, "/man1/man12-wf3.egg": {"target": "L11.R0003.A0004.egg"}, "/man1/man12-wf10.egg": {"target": "L11.R0003.A0001.egg"}, "/man1/man12-wf7.egg": {"target": "L11.R0003.A0002.egg"}, "/man1/man12-wf6.egg": {"target": "L11.R0003.A0005.egg"}, "/man1/man12-wf4.egg": {"target": "L11.R0003.A0006.egg"}, "/man1/man12-wf2.egg": {"target": "L11.R0003.A0008.egg"}, "/man1/man12-wf9.egg": {"target": "L11.R0003.A0007.egg"}}, "animation_size": 9}}, "/man0/man0.egg": {"target": "L11.R0006.egg", "data": {"anim_count": 10, "animations": {"/man0/man0-wf4.egg": {"target": "L11.R0006.A0004.egg"}, "/man0/man0-wf.egg": {"target": "L11.R0006.A0008.egg"}, "/man0/man0-wf8.egg": {"target": "L11.R0006.A0007.egg"}, "/man0/man0-wf2.egg": {"target": "L11.R0006.A0006.egg"}, "/man0/man0-wf7.egg": {"target": "L11.R0006.A0003.egg"}, "/man0/man0-wf5.egg": {"target": "L11.R0006.A0002.egg"}, "/man0/man0-wf6.egg": {"target": "L11.R0006.A0009.egg"}, "/man0/man0-wf9.egg": {"target": "L11.R0006.A0005.egg"}, "/man0/man0-wf10.egg": {"target": "L11.R0006.A0000.egg"}, "/man0/man0-wf3.egg": {"target": "L11.R0006.A0001.egg"}}, "animation_size": 10}}, "/woman2/women22.egg": {"target": "L11.R0000.egg", "data": {"anim_count": 9, "animations": {"/woman2/women22-wf7.egg": {"target": "L11.R0000.A0007.egg"}, "/woman2/women22-wf4.egg": {"target": "L11.R0000.A0000.egg"}, "/woman2/women22-wf6.egg": {"target": "L11.R0000.A0001.egg"}, "/woman2/women22-wf10.egg": {"target": "L11.R0000.A0005.egg"}, "/woman2/women22-wf9.egg": {"target": "L11.R0000.A0008.egg"}, "/woman2/women22-wf5.egg": {"target": "L11.R0000.A0002.egg"}, "/woman2/women22-wf8.egg": {"target": "L11.R0000.A0003.egg"}, "/woman2/women22-wf2.egg": {"target": "L11.R0000.A0004.egg"}, "/woman2/women22-wf3.egg": {"target": "L11.R0000.A0006.egg"}}, "animation_size": 9}}, "/woman1/woman12.egg": {"target": "L11.R0004.egg", "data": {"anim_count": 9, "animations": {"/woman1/woman12-wf4.egg": {"target": "L11.R0004.A0006.egg"}, "/woman1/woman12-wf8.egg": {"target": "L11.R0004.A0000.egg"}, "/woman1/woman12-wf2.egg": {"target": "L11.R0004.A0002.egg"}, "/woman1/woman12-wf10.egg": {"target": "L11.R0004.A0001.egg"}, "/woman1/woman12-wf3.egg": {"target": "L11.R0004.A0005.egg"}, "/woman1/woman12-wf5.egg": {"target": "L11.R0004.A0008.egg"}, "/woman1/woman12-wf7.egg": {"target": "L11.R0004.A0003.egg"}, "/woman1/woman12-wf6.egg": {"target": "L11.R0004.A0004.egg"}, "/woman1/woman12-wf9.egg": {"target": "L11.R0004.A0007.egg"}}, "animation_size": 9}}}, "anim_count": 50, "rig_count": 9, "rig_size": 9}}, "ts2": {"target": "L08", "data": {"rigs": {"/woman1/woman1ts2.egg": {"target": "L08.R0004.egg", "data": {"anim_count": 1, "animations": {"/woman1/woman1ts2-ts2.egg": {"target": "L08.R0004.A0000.egg"}}, "animation_size": 1}}, "/man2/man2ts2.egg": {"target": "L08.R0008.egg", "data": {"anim_count": 1, "animations": {"/man2/man2ts2-ts2.egg": {"target": "L08.R0008.A0000.egg"}}, "animation_size": 1}}, "/woman2/women22ts2.egg": {"target": "L08.R0000.egg", "data": {"anim_count": 5, "animations": {"/woman2/women22ts2-ts26.egg": {"target": "L08.R0000.A0000.egg"}, "/woman2/women22ts2-ts27.egg": {"target": "L08.R0000.A0002.egg"}, "/woman2/women22ts2-ts210.egg": {"target": "L08.R0000.A0004.egg"}, "/woman2/women22ts2-ts29.egg": {"target": "L08.R0000.A0003.egg"}, "/woman2/women22ts2-ts28.egg": {"target": "L08.R0000.A0001.egg"}}, "animation_size": 5}}, "/man1/man12ts2.egg": {"target": "L08.R0002.egg", "data": {"anim_count": 5, "animations": {"/man1/man12ts2-ts29.egg": {"target": "L08.R0002.A0004.egg"}, "/man1/man12ts2-ts210.egg": {"target": "L08.R0002.A0000.egg"}, "/man1/man12ts2-ts26.egg": {"target": "L08.R0002.A0001.egg"}, "/man1/man12ts2-ts27.egg": {"target": "L08.R0002.A0002.egg"}, "/man1/man12ts2-ts28.egg": {"target": "L08.R0002.A0003.egg"}}, "animation_size": 5}}, "/woman1/woman12ts2.egg": {"target": "L08.R0005.egg", "data": {"anim_count": 4, "animations": {"/woman1/woman12ts2-ts210.egg": {"target": "L08.R0005.A0001.egg"}, "/woman1/woman12ts2-ts28.egg": {"target": "L08.R0005.A0000.egg"}, "/woman1/woman12ts2-ts27.egg": {"target": "L08.R0005.A0003.egg"}, "/woman1/woman12ts2-ts29.egg": {"target": "L08.R0005.A0002.egg"}}, "animation_size": 4}}, "/man1/man1ts2.egg": {"target": "L08.R0003.egg", "data": {"anim_count": 1, "animations": {"/man1/man1ts2-ts2.egg": {"target": "L08.R0003.A0000.egg"}}, "animation_size": 1}}, "/woman2/woman2ts2.egg": {"target": "L08.R0001.egg", "data": {"anim_count": 1, "animations": {"/woman2/woman2ts2-ts2.egg": {"target": "L08.R0001.A0000.egg"}}, "animation_size": 1}}, "/man0/man0ts2.egg": {"target": "L08.R0006.egg", "data": {"anim_count": 4, "animations": {"/man0/man0ts2-ts27.egg": {"target": "L08.R0006.A0000.egg"}, "/man0/man0ts2-ts210.egg": {"target": "L08.R0006.A0002.egg"}, "/man0/man0ts2-ts28.egg": {"target": "L08.R0006.A0003.egg"}, "/man0/man0ts2-ts29.egg": {"target": "L08.R0006.A0001.egg"}}, "animation_size": 4}}, "/man2/man22ts2.egg": {"target": "L08.R0007.egg", "data": {"anim_count": 5, "animations": {"/man2/man22ts2-ts29.egg": {"target": "L08.R0007.A0000.egg"}, "/man2/man22ts2-ts26.egg": {"target": "L08.R0007.A0002.egg"}, "/man2/man22ts2-ts210.egg": {"target": "L08.R0007.A0001.egg"}, "/man2/man22ts2-ts27.egg": {"target": "L08.R0007.A0003.egg"}, "/man2/man22ts2-ts28.egg": {"target": "L08.R0007.A0004.egg"}}, "animation_size": 5}}}, "anim_count": 27, "rig_count": 9, "rig_size": 9}}, "pm1": {"target": "L05", "data": {"rigs": {"/man1/man12pm1.egg": {"target": "L05.R0002.egg", "data": {"anim_count": 7, "animations": {"/man1/man12pm1-pm14.egg": {"target": "L05.R0002.A0000.egg"}, "/man1/man12pm1-pm12.egg": {"target": "L05.R0002.A0005.egg"}, "/man1/man12pm1-pm13.egg": {"target": "L05.R0002.A0002.egg"}, "/man1/man12pm1-pm18.egg": {"target": "L05.R0002.A0003.egg"}, "/man1/man12pm1-pm15.egg": {"target": "L05.R0002.A0004.egg"}, "/man1/man12pm1-pm17.egg": {"target": "L05.R0002.A0001.egg"}, "/man1/man12pm1-pm16.egg": {"target": "L05.R0002.A0006.egg"}}, "animation_size": 7}}, "/woman2/woman2pm1.egg": {"target": "L05.R0001.egg", "data": {"anim_count": 1, "animations": {"/woman2/woman2pm1-pm1.egg": {"target": "L05.R0001.A0000.egg"}}, "animation_size": 1}}, "/man1/man1pm1.egg": {"target": "L05.R0004.egg", "data": {"anim_count": 1, "animations": {"/man1/man1pm1-pm1.egg": {"target": "L05.R0004.A0000.egg"}}, "animation_size": 1}}, "/woman1/woman1pm1.egg": {"target": "L05.R0006.egg", "data": {"anim_count": 1, "animations": {"/woman1/woman1pm1-pm1.egg": {"target": "L05.R0006.A0000.egg"}}, "animation_size": 1}}, "/man2/man22pm1.egg": {"target": "L05.R0008.egg", "data": {"anim_count": 8, "animations": {"/man2/man22pm1-pm18.egg": {"target": "L05.R0008.A0000.egg"}, "/man2/man22pm1-pm19.egg": {"target": "L05.R0008.A0004.egg"}, "/man2/man22pm1-pm12.egg": {"target": "L05.R0008.A0001.egg"}, "/man2/man22pm1-pm17.egg": {"target": "L05.R0008.A0006.egg"}, "/man2/man22pm1-pm15.egg": {"target": "L05.R0008.A0003.egg"}, "/man2/man22pm1-pm14.egg": {"target": "L05.R0008.A0002.egg"}, "/man2/man22pm1-pm13.egg": {"target": "L05.R0008.A0005.egg"}, "/man2/man22pm1-pm16.egg": {"target": "L05.R0008.A0007.egg"}}, "animation_size": 8}}, "/man0/man0pm1.egg": {"target": "L05.R0007.egg", "data": {"anim_count": 10, "animations": {"/man0/man0pm1-pm17.egg": {"target": "L05.R0007.A0005.egg"}, "/man0/man0pm1-pm110.egg": {"target": "L05.R0007.A0007.egg"}, "/man0/man0pm1-pm13.egg": {"target": "L05.R0007.A0000.egg"}, "/man0/man0pm1-pm16.egg": {"target": "L05.R0007.A0009.egg"}, "/man0/man0pm1-pm12.egg": {"target": "L05.R0007.A0003.egg"}, "/man0/man0pm1-pm15.egg": {"target": "L05.R0007.A0002.egg"}, "/man0/man0pm1-pm19.egg": {"target": "L05.R0007.A0008.egg"}, "/man0/man0pm1-pm11.egg": {"target": "L05.R0007.A0004.egg"}, "/man0/man0pm1-pm18.egg": {"target": "L05.R0007.A0006.egg"}, "/man0/man0pm1-pm14.egg": {"target": "L05.R0007.A0001.egg"}}, "animation_size": 10}}, "/woman1/woman12pm1.egg": {"target": "L05.R0005.egg", "data": {"anim_count": 9, "animations": {"/woman1/woman12pm1-pm16.egg": {"target": "L05.R0005.A0002.egg"}, "/woman1/woman12pm1-pm15.egg": {"target": "L05.R0005.A0000.egg"}, "/woman1/woman12pm1-pm19.egg": {"target": "L05.R0005.A0004.egg"}, "/woman1/woman12pm1-pm14.egg": {"target": "L05.R0005.A0006.egg"}, "/woman1/woman12pm1-pm18.egg": {"target": "L05.R0005.A0001.egg"}, "/woman1/woman12pm1-pm12.egg": {"target": "L05.R0005.A0007.egg"}, "/woman1/woman12pm1-pm13.egg": {"target": "L05.R0005.A0003.egg"}, "/woman1/woman12pm1-pm17.egg": {"target": "L05.R0005.A0008.egg"}, "/woman1/woman12pm1-pm110.egg": {"target": "L05.R0005.A0005.egg"}}, "animation_size": 9}}, "/man2/man2pm1.egg": {"target": "L05.R0009.egg", "data": {"anim_count": 1, "animations": {"/man2/man2pm1-pm1.egg": {"target": "L05.R0009.A0000.egg"}}, "animation_size": 1}}, "/man1/man13pm1.egg": {"target": "L05.R0003.egg", "data": {"anim_count": 2, "animations": {"/man1/man13pm1-pm110.egg": {"target": "L05.R0003.A0001.egg"}, "/man1/man13pm1-pm19.egg": {"target": "L05.R0003.A0000.egg"}}, "animation_size": 2}}, "/woman2/women22pm1.egg": {"target": "L05.R0000.egg", "data": {"anim_count": 9, "animations": {"/woman2/women22pm1-pm17.egg": {"target": "L05.R0000.A0005.egg"}, "/woman2/women22pm1-pm12.egg": {"target": "L05.R0000.A0003.egg"}, "/woman2/women22pm1-pm16.egg": {"target": "L05.R0000.A0000.egg"}, "/woman2/women22pm1-pm19.egg": {"target": "L05.R0000.A0001.egg"}, "/woman2/women22pm1-pm18.egg": {"target": "L05.R0000.A0008.egg"}, "/woman2/women22pm1-pm15.egg": {"target": "L05.R0000.A0004.egg"}, "/woman2/women22pm1-pm110.egg": {"target": "L05.R0000.A0002.egg"}, "/woman2/women22pm1-pm13.egg": {"target": "L05.R0000.A0006.egg"}, "/woman2/women22pm1-pm14.egg": {"target": "L05.R0000.A0007.egg"}}, "animation_size": 9}}}, "anim_count": 49, "rig_count": 10, "rig_size": 10}}, "mt2": {"target": "L04", "data": {"rigs": {"/woman2/woman2mt2.egg": {"target": "L04.R0001.egg", "data": {"anim_count": 1, "animations": {"/woman2/woman2mt2-mt2.egg": {"target": "L04.R0001.A0000.egg"}}, "animation_size": 1}}, "/man2/man2mt2.egg": {"target": "L04.R0008.egg", "data": {"anim_count": 1, "animations": {"/man2/man2mt2-mt2.egg": {"target": "L04.R0008.A0000.egg"}}, "animation_size": 1}}, "/man0/man0mt2.egg": {"target": "L04.R0006.egg", "data": {"anim_count": 10, "animations": {"/man0/man0mt2-mt23.egg": {"target": "L04.R0006.A0003.egg"}, "/man0/man0mt2-mt24.egg": {"target": "L04.R0006.A0002.egg"}, "/man0/man0mt2-mt29.egg": {"target": "L04.R0006.A0004.egg"}, "/man0/man0mt2-mt26.egg": {"target": "L04.R0006.A0001.egg"}, "/man0/man0mt2-mt21.egg": {"target": "L04.R0006.A0000.egg"}, "/man0/man0mt2-mt25.egg": {"target": "L04.R0006.A0005.egg"}, "/man0/man0mt2-mt28.egg": {"target": "L04.R0006.A0009.egg"}, "/man0/man0mt2-mt22.egg": {"target": "L04.R0006.A0007.egg"}, "/man0/man0mt2-mt27.egg": {"target": "L04.R0006.A0008.egg"}, "/man0/man0mt2-mt210.egg": {"target": "L04.R0006.A0006.egg"}}, "animation_size": 10}}, "/woman2/women22mt2.egg": {"target": "L04.R0000.egg", "data": {"anim_count": 9, "animations": {"/woman2/women22mt2-mt25.egg": {"target": "L04.R0000.A0005.egg"}, "/woman2/women22mt2-mt26.egg": {"target": "L04.R0000.A0006.egg"}, "/woman2/women22mt2-mt22.egg": {"target": "L04.R0000.A0008.egg"}, "/woman2/women22mt2-mt210.egg": {"target": "L04.R0000.A0003.egg"}, "/woman2/women22mt2-mt28.egg": {"target": "L04.R0000.A0002.egg"}, "/woman2/women22mt2-mt29.egg": {"target": "L04.R0000.A0004.egg"}, "/woman2/women22mt2-mt24.egg": {"target": "L04.R0000.A0001.egg"}, "/woman2/women22mt2-mt27.egg": {"target": "L04.R0000.A0007.egg"}, "/woman2/women22mt2-mt23.egg": {"target": "L04.R0000.A0000.egg"}}, "animation_size": 9}}, "/man1/man12mt2.egg": {"target": "L04.R0002.egg", "data": {"anim_count": 9, "animations": {"/man1/man12mt2-mt22.egg": {"target": "L04.R0002.A0001.egg"}, "/man1/man12mt2-mt25.egg": {"target": "L04.R0002.A0003.egg"}, "/man1/man12mt2-mt26.egg": {"target": "L04.R0002.A0007.egg"}, "/man1/man12mt2-mt24.egg": {"target": "L04.R0002.A0006.egg"}, "/man1/man12mt2-mt23.egg": {"target": "L04.R0002.A0005.egg"}, "/man1/man12mt2-mt28.egg": {"target": "L04.R0002.A0000.egg"}, "/man1/man12mt2-mt29.egg": {"target": "L04.R0002.A0004.egg"}, "/man1/man12mt2-mt210.egg": {"target": "L04.R0002.A0008.egg"}, "/man1/man12mt2-mt27.egg": {"target": "L04.R0002.A0002.egg"}}, "animation_size": 9}}, "/woman1/woman1mt2.egg": {"target": "L04.R0005.egg", "data": {"anim_count": 1, "animations": {"/woman1/woman1mt2-mt2.egg": {"target": "L04.R0005.A0000.egg"}}, "animation_size": 1}}, "/woman1/woman12mt2.egg": {"target": "L04.R0004.egg", "data": {"anim_count": 9, "animations": {"/woman1/woman12mt2-mt26.egg": {"target": "L04.R0004.A0003.egg"}, "/woman1/woman12mt2-mt210.egg": {"target": "L04.R0004.A0001.egg"}, "/woman1/woman12mt2-mt25.egg": {"target": "L04.R0004.A0000.egg"}, "/woman1/woman12mt2-mt29.egg": {"target": "L04.R0004.A0004.egg"}, "/woman1/woman12mt2-mt23.egg": {"target": "L04.R0004.A0008.egg"}, "/woman1/woman12mt2-mt24.egg": {"target": "L04.R0004.A0006.egg"}, "/woman1/woman12mt2-mt22.egg": {"target": "L04.R0004.A0007.egg"}, "/woman1/woman12mt2-mt27.egg": {"target": "L04.R0004.A0005.egg"}, "/woman1/woman12mt2-mt28.egg": {"target": "L04.R0004.A0002.egg"}}, "animation_size": 9}}, "/man1/man1mt2.egg": {"target": "L04.R0003.egg", "data": {"anim_count": 1, "animations": {"/man1/man1mt2-mt2.egg": {"target": "L04.R0003.A0000.egg"}}, "animation_size": 1}}, "/man2/man22mt2.egg": {"target": "L04.R0007.egg", "data": {"anim_count": 9, "animations": {"/man2/man22mt2-mt26.egg": {"target": "L04.R0007.A0004.egg"}, "/man2/man22mt2-mt28.egg": {"target": "L04.R0007.A0006.egg"}, "/man2/man22mt2-mt24.egg": {"target": "L04.R0007.A0003.egg"}, "/man2/man22mt2-mt22.egg": {"target": "L04.R0007.A0001.egg"}, "/man2/man22mt2-mt210.egg": {"target": "L04.R0007.A0005.egg"}, "/man2/man22mt2-mt29.egg": {"target": "L04.R0007.A0008.egg"}, "/man2/man22mt2-mt23.egg": {"target": "L04.R0007.A0000.egg"}, "/man2/man22mt2-mt27.egg": {"target": "L04.R0007.A0007.egg"}, "/man2/man22mt2-mt25.egg": {"target": "L04.R0007.A0002.egg"}}, "animation_size": 9}}}, "anim_count": 50, "rig_count": 9, "rig_size": 9}}, "wd": {"target": "L10", "data": {"rigs": {"/man1/man13wd.egg": {"target": "L10.R0003.egg", "data": {"anim_count": 2, "animations": {"/man1/man13wd-wd10.egg": {"target": "L10.R0003.A0001.egg"}, "/man1/man13wd-wd9.egg": {"target": "L10.R0003.A0000.egg"}}, "animation_size": 2}}, "/man1/man12wd.egg": {"target": "L10.R0002.egg", "data": {"anim_count": 7, "animations": {"/man1/man12wd-wd6.egg": {"target": "L10.R0002.A0005.egg"}, "/man1/man12wd-wd4.egg": {"target": "L10.R0002.A0001.egg"}, "/man1/man12wd-wd8.egg": {"target": "L10.R0002.A0004.egg"}, "/man1/man12wd-wd7.egg": {"target": "L10.R0002.A0002.egg"}, "/man1/man12wd-wd2.egg": {"target": "L10.R0002.A0003.egg"}, "/man1/man12wd-wd3.egg": {"target": "L10.R0002.A0000.egg"}, "/man1/man12wd-wd5.egg": {"target": "L10.R0002.A0006.egg"}}, "animation_size": 7}}, "/woman2/women22wd.egg": {"target": "L10.R0000.egg", "data": {"anim_count": 9, "animations": {"/woman2/women22wd-wd10.egg": {"target": "L10.R0000.A0001.egg"}, "/woman2/women22wd-wd3.egg": {"target": "L10.R0000.A0008.egg"}, "/woman2/women22wd-wd4.egg": {"target": "L10.R0000.A0002.egg"}, "/woman2/women22wd-wd6.egg": {"target": "L10.R0000.A0003.egg"}, "/woman2/women22wd-wd5.egg": {"target": "L10.R0000.A0004.egg"}, "/woman2/women22wd-wd2.egg": {"target": "L10.R0000.A0006.egg"}, "/woman2/women22wd-wd7.egg": {"target": "L10.R0000.A0005.egg"}, "/woman2/women22wd-wd9.egg": {"target": "L10.R0000.A0000.egg"}, "/woman2/women22wd-wd8.egg": {"target": "L10.R0000.A0007.egg"}}, "animation_size": 9}}, "/man1/man1wd.egg": {"target": "L10.R0004.egg", "data": {"anim_count": 1, "animations": {"/man1/man1wd-wd.egg": {"target": "L10.R0004.A0000.egg"}}, "animation_size": 1}}, "/man2/man2wd.egg": {"target": "L10.R0009.egg", "data": {"anim_count": 1, "animations": {"/man2/man2wd-wd.egg": {"target": "L10.R0009.A0000.egg"}}, "animation_size": 1}}, "/woman1/woman1wd.egg": {"target": "L10.R0006.egg", "data": {"anim_count": 1, "animations": {"/woman1/woman1wd-wd.egg": {"target": "L10.R0006.A0000.egg"}}, "animation_size": 1}}, "/man0/man0wd.egg": {"target": "L10.R0007.egg", "data": {"anim_count": 10, "animations": {"/man0/man0wd-wd10.egg": {"target": "L10.R0007.A0002.egg"}, "/man0/man0wd-wd9.egg": {"target": "L10.R0007.A0007.egg"}, "/man0/man0wd-wd5.egg": {"target": "L10.R0007.A0004.egg"}, "/man0/man0wd-wd6.egg": {"target": "L10.R0007.A0001.egg"}, "/man0/man0wd-wd8.egg": {"target": "L10.R0007.A0006.egg"}, "/man0/man0wd-wd7.egg": {"target": "L10.R0007.A0005.egg"}, "/man0/man0wd-wd1.egg": {"target": "L10.R0007.A0000.egg"}, "/man0/man0wd-wd2.egg": {"target": "L10.R0007.A0009.egg"}, "/man0/man0wd-wd3.egg": {"target": "L10.R0007.A0003.egg"}, "/man0/man0wd-wd4.egg": {"target": "L10.R0007.A0008.egg"}}, "animation_size": 10}}, "/woman1/woman12wd.egg": {"target": "L10.R0005.egg", "data": {"anim_count": 9, "animations": {"/woman1/woman12wd-wd8.egg": {"target": "L10.R0005.A0004.egg"}, "/woman1/woman12wd-wd9.egg": {"target": "L10.R0005.A0007.egg"}, "/woman1/woman12wd-wd3.egg": {"target": "L10.R0005.A0003.egg"}, "/woman1/woman12wd-wd2.egg": {"target": "L10.R0005.A0008.egg"}, "/woman1/woman12wd-wd6.egg": {"target": "L10.R0005.A0006.egg"}, "/woman1/woman12wd-wd4.egg": {"target": "L10.R0005.A0005.egg"}, "/woman1/woman12wd-wd10.egg": {"target": "L10.R0005.A0001.egg"}, "/woman1/woman12wd-wd5.egg": {"target": "L10.R0005.A0000.egg"}, "/woman1/woman12wd-wd7.egg": {"target": "L10.R0005.A0002.egg"}}, "animation_size": 9}}, "/woman2/woman2wd.egg": {"target": "L10.R0001.egg", "data": {"anim_count": 1, "animations": {"/woman2/woman2wd-wd.egg": {"target": "L10.R0001.A0000.egg"}}, "animation_size": 1}}, "/man2/man22wd.egg": {"target": "L10.R0008.egg", "data": {"anim_count": 9, "animations": {"/man2/man22wd-wd2.egg": {"target": "L10.R0008.A0008.egg"}, "/man2/man22wd-wd7.egg": {"target": "L10.R0008.A0004.egg"}, "/man2/man22wd-wd4.egg": {"target": "L10.R0008.A0000.egg"}, "/man2/man22wd-wd6.egg": {"target": "L10.R0008.A0005.egg"}, "/man2/man22wd-wd5.egg": {"target": "L10.R0008.A0006.egg"}, "/man2/man22wd-wd10.egg": {"target": "L10.R0008.A0002.egg"}, "/man2/man22wd-wd8.egg": {"target": "L10.R0008.A0003.egg"}, "/man2/man22wd-wd3.egg": {"target": "L10.R0008.A0001.egg"}, "/man2/man22wd-wd9.egg": {"target": "L10.R0008.A0007.egg"}}, "animation_size": 9}}}, "anim_count": 50, "rig_count": 10, "rig_size": 10}}, "ts1": {"target": "L08", "data": {"rigs": {"/woman2/woman2ts1.egg": {"target": "L08.R0001.egg", "data": {"anim_count": 1, "animations": {"/woman2/woman2ts1-ts1.egg": {"target": "L08.R0001.A0000.egg"}}, "animation_size": 1}}, "/man2/man22ts1.egg": {"target": "L08.R0007.egg", "data": {"anim_count": 4, "animations": {"/man2/man22ts1-ts14.egg": {"target": "L08.R0007.A0000.egg"}, "/man2/man22ts1-ts13.egg": {"target": "L08.R0007.A0002.egg"}, "/man2/man22ts1-ts12.egg": {"target": "L08.R0007.A0001.egg"}, "/man2/man22ts1-ts15.egg": {"target": "L08.R0007.A0003.egg"}}, "animation_size": 4}}, "/man1/man12ts1.egg": {"target": "L08.R0002.egg", "data": {"anim_count": 3, "animations": {"/man1/man12ts1-ts12.egg": {"target": "L08.R0002.A0000.egg"}, "/man1/man12ts1-ts14.egg": {"target": "L08.R0002.A0001.egg"}, "/man1/man12ts1-ts13.egg": {"target": "L08.R0002.A0002.egg"}}, "animation_size": 3}}, "/woman1/woman12ts1.egg": {"target": "L08.R0004.egg", "data": {"anim_count": 5, "animations": {"/woman1/woman12ts1-ts16.egg": {"target": "L08.R0004.A0000.egg"}, "/woman1/woman12ts1-ts12.egg": {"target": "L08.R0004.A0004.egg"}, "/woman1/woman12ts1-ts14.egg": {"target": "L08.R0004.A0002.egg"}, "/woman1/woman12ts1-ts15.egg": {"target": "L08.R0004.A0003.egg"}, "/woman1/woman12ts1-ts13.egg": {"target": "L08.R0004.A0001.egg"}}, "animation_size": 5}}, "/woman2/women22ts1.egg": {"target": "L08.R0000.egg", "data": {"anim_count": 4, "animations": {"/woman2/women22ts1-ts15.egg": {"target": "L08.R0000.A0002.egg"}, "/woman2/women22ts1-ts14.egg": {"target": "L08.R0000.A0001.egg"}, "/woman2/women22ts1-ts13.egg": {"target": "L08.R0000.A0000.egg"}, "/woman2/women22ts1-ts12.egg": {"target": "L08.R0000.A0003.egg"}}, "animation_size": 4}}, "/man2/man2ts1.egg": {"target": "L08.R0008.egg", "data": {"anim_count": 1, "animations": {"/man2/man2ts1-ts1.egg": {"target": "L08.R0008.A0000.egg"}}, "animation_size": 1}}, "/man1/man1ts1.egg": {"target": "L08.R0003.egg", "data": {"anim_count": 1, "animations": {"/man1/man1ts1-ts1.egg": {"target": "L08.R0003.A0000.egg"}}, "animation_size": 1}}, "/man0/man0ts1.egg": {"target": "L08.R0006.egg", "data": {"anim_count": 6, "animations": {"/man0/man0ts1-ts15.egg": {"target": "L08.R0006.A0005.egg"}, "/man0/man0ts1-ts14.egg": {"target": "L08.R0006.A0004.egg"}, "/man0/man0ts1-ts13.egg": {"target": "L08.R0006.A0003.egg"}, "/man0/man0ts1-ts12.egg": {"target": "L08.R0006.A0001.egg"}, "/man0/man0ts1-ts16.egg": {"target": "L08.R0006.A0000.egg"}, "/man0/man0ts1-ts11.egg": {"target": "L08.R0006.A0002.egg"}}, "animation_size": 6}}, "/woman1/woman1ts1.egg": {"target": "L08.R0005.egg", "data": {"anim_count": 1, "animations": {"/woman1/woman1ts1-ts1.egg": {"target": "L08.R0005.A0000.egg"}}, "animation_size": 1}}}, "anim_count": 26, "rig_count": 9, "rig_size": 9}}, "pm2": {"target": "L06", "data": {"rigs": {"/woman1/woman12pm2.egg": {"target": "L06.R0005.egg", "data": {"anim_count": 5, "animations": {"/woman1/woman12pm2-pm24.egg": {"target": "L06.R0005.A0000.egg"}, "/woman1/woman12pm2-pm22.egg": {"target": "L06.R0005.A0002.egg"}, "/woman1/woman12pm2-pm26.egg": {"target": "L06.R0005.A0001.egg"}, "/woman1/woman12pm2-pm23.egg": {"target": "L06.R0005.A0004.egg"}, "/woman1/woman12pm2-pm25.egg": {"target": "L06.R0005.A0003.egg"}}, "animation_size": 5}}, "/man1/man1pm2.egg": {"target": "L06.R0003.egg", "data": {"anim_count": 1, "animations": {"/man1/man1pm2-pm2.egg": {"target": "L06.R0003.A0000.egg"}}, "animation_size": 1}}, "/woman2/women22pm2.egg": {"target": "L06.R0000.egg", "data": {"anim_count": 9, "animations": {"/woman2/women22pm2-pm25.egg": {"target": "L06.R0000.A0001.egg"}, "/woman2/women22pm2-pm23.egg": {"target": "L06.R0000.A0002.egg"}, "/woman2/women22pm2-pm28.egg": {"target": "L06.R0000.A0007.egg"}, "/woman2/women22pm2-pm210.egg": {"target": "L06.R0000.A0000.egg"}, "/woman2/women22pm2-pm24.egg": {"target": "L06.R0000.A0004.egg"}, "/woman2/women22pm2-pm22.egg": {"target": "L06.R0000.A0005.egg"}, "/woman2/women22pm2-pm29.egg": {"target": "L06.R0000.A0003.egg"}, "/woman2/women22pm2-pm27.egg": {"target": "L06.R0000.A0006.egg"}, "/woman2/women22pm2-pm26.egg": {"target": "L06.R0000.A0008.egg"}}, "animation_size": 9}}, "/woman1/woman1pm2.egg": {"target": "L06.R0007.egg", "data": {"anim_count": 1, "animations": {"/woman1/woman1pm2-pm2.egg": {"target": "L06.R0007.A0000.egg"}}, "animation_size": 1}}, "/woman1/woman13pm2.egg": {"target": "L06.R0006.egg", "data": {"anim_count": 4, "animations": {"/woman1/woman13pm2-pm28.egg": {"target": "L06.R0006.A0002.egg"}, "/woman1/woman13pm2-pm210.egg": {"target": "L06.R0006.A0001.egg"}, "/woman1/woman13pm2-pm27.egg": {"target": "L06.R0006.A0000.egg"}, "/woman1/woman13pm2-pm29.egg": {"target": "L06.R0006.A0003.egg"}}, "animation_size": 4}}, "/man0/man0pm2.egg": {"target": "L06.R0008.egg", "data": {"anim_count": 10, "animations": {"/man0/man0pm2-pm21.egg": {"target": "L06.R0008.A0008.egg"}, "/man0/man0pm2-pm23.egg": {"target": "L06.R0008.A0003.egg"}, "/man0/man0pm2-pm22.egg": {"target": "L06.R0008.A0005.egg"}, "/man0/man0pm2-pm25.egg": {"target": "L06.R0008.A0001.egg"}, "/man0/man0pm2-pm29.egg": {"target": "L06.R0008.A0004.egg"}, "/man0/man0pm2-pm27.egg": {"target": "L06.R0008.A0009.egg"}, "/man0/man0pm2-pm26.egg": {"target": "L06.R0008.A0006.egg"}, "/man0/man0pm2-pm28.egg": {"target": "L06.R0008.A0002.egg"}, "/man0/man0pm2-pm210.egg": {"target": "L06.R0008.A0007.egg"}, "/man0/man0pm2-pm24.egg": {"target": "L06.R0008.A0000.egg"}}, "animation_size": 10}}, "/woman2/woman2pm2.egg": {"target": "L06.R0001.egg", "data": {"anim_count": 1, "animations": {"/woman2/woman2pm2-pm2.egg": {"target": "L06.R0001.A0000.egg"}}, "animation_size": 1}}, "/man1/man12pm2.egg": {"target": "L06.R0002.egg", "data": {"anim_count": 8, "animations": {"/man1/man12pm2-pm25.egg": {"target": "L06.R0002.A0000.egg"}, "/man1/man12pm2-pm23.egg": {"target": "L06.R0002.A0007.egg"}, "/man1/man12pm2-pm28.egg": {"target": "L06.R0002.A0002.egg"}, "/man1/man12pm2-pm27.egg": {"target": "L06.R0002.A0003.egg"}, "/man1/man12pm2-pm24.egg": {"target": "L06.R0002.A0001.egg"}, "/man1/man12pm2-pm22.egg": {"target": "L06.R0002.A0004.egg"}, "/man1/man12pm2-pm26.egg": {"target": "L06.R0002.A0005.egg"}, "/man1/man12pm2-pm29.egg": {"target": "L06.R0002.A0006.egg"}}, "animation_size": 8}}, "/man2/man22pm2.egg": {"target": "L06.R0009.egg", "data": {"anim_count": 9, "animations": {"/man2/man22pm2-pm25.egg": {"target": "L06.R0009.A0001.egg"}, "/man2/man22pm2-pm24.egg": {"target": "L06.R0009.A0007.egg"}, "/man2/man22pm2-pm210.egg": {"target": "L06.R0009.A0002.egg"}, "/man2/man22pm2-pm23.egg": {"target": "L06.R0009.A0006.egg"}, "/man2/man22pm2-pm22.egg": {"target": "L06.R0009.A0004.egg"}, "/man2/man22pm2-pm29.egg": {"target": "L06.R0009.A0003.egg"}, "/man2/man22pm2-pm27.egg": {"target": "L06.R0009.A0005.egg"}, "/man2/man22pm2-pm28.egg": {"target": "L06.R0009.A0008.egg"}, "/man2/man22pm2-pm26.egg": {"target": "L06.R0009.A0000.egg"}}, "animation_size": 9}}, "/man1/man13pm2.egg": {"target": "L06.R0004.egg", "data": {"anim_count": 1, "animations": {"/man1/man13pm2-pm210.egg": {"target": "L06.R0004.A0000.egg"}}, "animation_size": 1}}, "/man2/man2pm2.egg": {"target": "L06.R0010.egg", "data": {"anim_count": 1, "animations": {"/man2/man2pm2-pm2.egg": {"target": "L06.R0010.A0000.egg"}}, "animation_size": 1}}}, "anim_count": 50, "rig_count": 11, "rig_size": 11}}, "wtv": {"target": "L12", "data": {"rigs": {"/man2/man22wtv.egg": {"target": "L12.R0007.egg", "data": {"anim_count": 9, "animations": {"/man2/man22wtv-wtv5.egg": {"target": "L12.R0007.A0006.egg"}, "/man2/man22wtv-wtv10.egg": {"target": "L12.R0007.A0005.egg"}, "/man2/man22wtv-wtv8.egg": {"target": "L12.R0007.A0001.egg"}, "/man2/man22wtv-wtv2.egg": {"target": "L12.R0007.A0004.egg"}, "/man2/man22wtv-wtv9.egg": {"target": "L12.R0007.A0003.egg"}, "/man2/man22wtv-wtv3.egg": {"target": "L12.R0007.A0008.egg"}, "/man2/man22wtv-wtv7.egg": {"target": "L12.R0007.A0007.egg"}, "/man2/man22wtv-wtv6.egg": {"target": "L12.R0007.A0002.egg"}, "/man2/man22wtv-wtv4.egg": {"target": "L12.R0007.A0000.egg"}}, "animation_size": 9}}, "/woman1/woman12wtv.egg": {"target": "L12.R0004.egg", "data": {"anim_count": 9, "animations": {"/woman1/woman12wtv-wtv2.egg": {"target": "L12.R0004.A0008.egg"}, "/woman1/woman12wtv-wtv6.egg": {"target": "L12.R0004.A0006.egg"}, "/woman1/woman12wtv-wtv5.egg": {"target": "L12.R0004.A0002.egg"}, "/woman1/woman12wtv-wtv10.egg": {"target": "L12.R0004.A0003.egg"}, "/woman1/woman12wtv-wtv9.egg": {"target": "L12.R0004.A0007.egg"}, "/woman1/woman12wtv-wtv7.egg": {"target": "L12.R0004.A0005.egg"}, "/woman1/woman12wtv-wtv4.egg": {"target": "L12.R0004.A0004.egg"}, "/woman1/woman12wtv-wtv3.egg": {"target": "L12.R0004.A0000.egg"}, "/woman1/woman12wtv-wtv8.egg": {"target": "L12.R0004.A0001.egg"}}, "animation_size": 9}}, "/man1/man1wtv.egg": {"target": "L12.R0003.egg", "data": {"anim_count": 1, "animations": {"/man1/man1wtv-wtv.egg": {"target": "L12.R0003.A0000.egg"}}, "animation_size": 1}}, "/woman2/women22wtv.egg": {"target": "L12.R0000.egg", "data": {"anim_count": 9, "animations": {"/woman2/women22wtv-wtv2.egg": {"target": "L12.R0000.A0003.egg"}, "/woman2/women22wtv-wtv6.egg": {"target": "L12.R0000.A0006.egg"}, "/woman2/women22wtv-wtv5.egg": {"target": "L12.R0000.A0004.egg"}, "/woman2/women22wtv-wtv10.egg": {"target": "L12.R0000.A0008.egg"}, "/woman2/women22wtv-wtv7.egg": {"target": "L12.R0000.A0000.egg"}, "/woman2/women22wtv-wtv4.egg": {"target": "L12.R0000.A0007.egg"}, "/woman2/women22wtv-wtv9.egg": {"target": "L12.R0000.A0005.egg"}, "/woman2/women22wtv-wtv8.egg": {"target": "L12.R0000.A0002.egg"}, "/woman2/women22wtv-wtv3.egg": {"target": "L12.R0000.A0001.egg"}}, "animation_size": 9}}, "/woman1/woman1wtv.egg": {"target": "L12.R0005.egg", "data": {"anim_count": 1, "animations": {"/woman1/woman1wtv-wtv.egg": {"target": "L12.R0005.A0000.egg"}}, "animation_size": 1}}, "/man0/man0wtv.egg": {"target": "L12.R0006.egg", "data": {"anim_count": 10, "animations": {"/man0/man0wtv-wtv2.egg": {"target": "L12.R0006.A0002.egg"}, "/man0/man0wtv-wtv8.egg": {"target": "L12.R0006.A0004.egg"}, "/man0/man0wtv-wtv5.egg": {"target": "L12.R0006.A0006.egg"}, "/man0/man0wtv-wtv9.egg": {"target": "L12.R0006.A0000.egg"}, "/man0/man0wtv-wtv7.egg": {"target": "L12.R0006.A0003.egg"}, "/man0/man0wtv-wtv6.egg": {"target": "L12.R0006.A0008.egg"}, "/man0/man0wtv-wtv3.egg": {"target": "L12.R0006.A0005.egg"}, "/man0/man0wtv-wtv10.egg": {"target": "L12.R0006.A0001.egg"}, "/man0/man0wtv-wtv1.egg": {"target": "L12.R0006.A0009.egg"}, "/man0/man0wtv-wtv4.egg": {"target": "L12.R0006.A0007.egg"}}, "animation_size": 10}}, "/man2/man2wtv.egg": {"target": "L12.R0008.egg", "data": {"anim_count": 1, "animations": {"/man2/man2wtv-wtv.egg": {"target": "L12.R0008.A0000.egg"}}, "animation_size": 1}}, "/woman2/woman2wtv.egg": {"target": "L12.R0001.egg", "data": {"anim_count": 1, "animations": {"/woman2/woman2wtv-wtv.egg": {"target": "L12.R0001.A0000.egg"}}, "animation_size": 1}}, "/man1/man12wtv.egg": {"target": "L12.R0002.egg", "data": {"anim_count": 9, "animations": {"/man1/man12wtv-wtv3.egg": {"target": "L12.R0002.A0002.egg"}, "/man1/man12wtv-wtv8.egg": {"target": "L12.R0002.A0007.egg"}, "/man1/man12wtv-wtv7.egg": {"target": "L12.R0002.A0001.egg"}, "/man1/man12wtv-wtv9.egg": {"target": "L12.R0002.A0003.egg"}, "/man1/man12wtv-wtv6.egg": {"target": "L12.R0002.A0005.egg"}, "/man1/man12wtv-wtv4.egg": {"target": "L12.R0002.A0000.egg"}, "/man1/man12wtv-wtv10.egg": {"target": "L12.R0002.A0004.egg"}, "/man1/man12wtv-wtv2.egg": {"target": "L12.R0002.A0008.egg"}, "/man1/man12wtv-wtv5.egg": {"target": "L12.R0002.A0006.egg"}}, "animation_size": 9}}}, "anim_count": 50, "rig_count": 9, "rig_size": 9}}, "mj": {"target": "L02", "data": {"rigs": {"/woman1/woman1mj1.egg": {"target": "L02.R0004.egg", "data": {"anim_count": 1, "animations": {"/woman1/woman1mj1-mj1.egg": {"target": "L02.R0004.A0000.egg"}}, "animation_size": 1}}, "/man2/man2mj1.egg": {"target": "L02.R0008.egg", "data": {"anim_count": 1, "animations": {"/man2/man2mj1-mj1.egg": {"target": "L02.R0008.A0000.egg"}}, "animation_size": 1}}, "/man0/man0mj.egg": {"target": "L02.R0006.egg", "data": {"anim_count": 9, "animations": {"/man0/man0mj-mj4.egg": {"target": "L02.R0006.A0005.egg"}, "/man0/man0mj-mj10.egg": {"target": "L02.R0006.A0003.egg"}, "/man0/man0mj-mj3.egg": {"target": "L02.R0006.A0002.egg"}, "/man0/man0mj-mj2.egg": {"target": "L02.R0006.A0006.egg"}, "/man0/man0mj-mj5.egg": {"target": "L02.R0006.A0007.egg"}, "/man0/man0mj-mj8.egg": {"target": "L02.R0006.A0004.egg"}, "/man0/man0mj-mj9.egg": {"target": "L02.R0006.A0000.egg"}, "/man0/man0mj-mj7.egg": {"target": "L02.R0006.A0001.egg"}, "/man0/man0mj-mj6.egg": {"target": "L02.R0006.A0008.egg"}}, "animation_size": 9}}, "/woman2/women22mj.egg": {"target": "L02.R0000.egg", "data": {"anim_count": 9, "animations": {"/woman2/women22mj-mj3.egg": {"target": "L02.R0000.A0007.egg"}, "/woman2/women22mj-mj5.egg": {"target": "L02.R0000.A0008.egg"}, "/woman2/women22mj-mj2.egg": {"target": "L02.R0000.A0001.egg"}, "/woman2/women22mj-mj10.egg": {"target": "L02.R0000.A0004.egg"}, "/woman2/women22mj-mj8.egg": {"target": "L02.R0000.A0006.egg"}, "/woman2/women22mj-mj7.egg": {"target": "L02.R0000.A0002.egg"}, "/woman2/women22mj-mj4.egg": {"target": "L02.R0000.A0005.egg"}, "/woman2/women22mj-mj6.egg": {"target": "L02.R0000.A0000.egg"}, "/woman2/women22mj-mj9.egg": {"target": "L02.R0000.A0003.egg"}}, "animation_size": 9}}, "/man2/man23mj.egg": {"target": "L02.R0007.egg", "data": {"anim_count": 8, "animations": {"/man2/man23mj-mj6.egg": {"target": "L02.R0007.A0006.egg"}, "/man2/man23mj-mj3.egg": {"target": "L02.R0007.A0004.egg"}, "/man2/man23mj-mj4.egg": {"target": "L02.R0007.A0005.egg"}, "/man2/man23mj-mj10.egg": {"target": "L02.R0007.A0007.egg"}, "/man2/man23mj-mj7.egg": {"target": "L02.R0007.A0002.egg"}, "/man2/man23mj-mj9.egg": {"target": "L02.R0007.A0000.egg"}, "/man2/man23mj-mj5.egg": {"target": "L02.R0007.A0001.egg"}, "/man2/man23mj-mj8.egg": {"target": "L02.R0007.A0003.egg"}}, "animation_size": 8}}, "/woman2/woman2mj1.egg": {"target": "L02.R0001.egg", "data": {"anim_count": 1, "animations": {"/woman2/woman2mj1-mj1.egg": {"target": "L02.R0001.A0000.egg"}}, "animation_size": 1}}, "/man1/man12mj.egg": {"target": "L02.R0002.egg", "data": {"anim_count": 9, "animations": {"/man1/man12mj-mj10.egg": {"target": "L02.R0002.A0008.egg"}, "/man1/man12mj-mj4.egg": {"target": "L02.R0002.A0002.egg"}, "/man1/man12mj-mj2.egg": {"target": "L02.R0002.A0004.egg"}, "/man1/man12mj-mj6.egg": {"target": "L02.R0002.A0003.egg"}, "/man1/man12mj-mj5.egg": {"target": "L02.R0002.A0001.egg"}, "/man1/man12mj-mj3.egg": {"target": "L02.R0002.A0005.egg"}, "/man1/man12mj-mj9.egg": {"target": "L02.R0002.A0007.egg"}, "/man1/man12mj-mj8.egg": {"target": "L02.R0002.A0006.egg"}, "/man1/man12mj-mj7.egg": {"target": "L02.R0002.A0000.egg"}}, "animation_size": 9}}, "/man1/man1mj1.egg": {"target": "L02.R0003.egg", "data": {"anim_count": 1, "animations": {"/man1/man1mj1-mj1.egg": {"target": "L02.R0003.A0000.egg"}}, "animation_size": 1}}, "/man2/man22mj.egg": {"target": "L02.R0009.egg", "data": {"anim_count": 1, "animations": {"/man2/man22mj-mj2.egg": {"target": "L02.R0009.A0000.egg"}}, "animation_size": 1}}, "/woman1/woman12mj.egg": {"target": "L02.R0005.egg", "data": {"anim_count": 9, "animations": {"/woman1/woman12mj-mj9.egg": {"target": "L02.R0005.A0007.egg"}, "/woman1/woman12mj-mj4.egg": {"target": "L02.R0005.A0005.egg"}, "/woman1/woman12mj-mj3.egg": {"target": "L02.R0005.A0001.egg"}, "/woman1/woman12mj-mj7.egg": {"target": "L02.R0005.A0003.egg"}, "/woman1/woman12mj-mj2.egg": {"target": "L02.R0005.A0006.egg"}, "/woman1/woman12mj-mj5.egg": {"target": "L02.R0005.A0002.egg"}, "/woman1/woman12mj-mj8.egg": {"target": "L02.R0005.A0004.egg"}, "/woman1/woman12mj-mj6.egg": {"target": "L02.R0005.A0000.egg"}, "/woman1/woman12mj-mj10.egg": {"target": "L02.R0005.A0008.egg"}}, "animation_size": 9}}}, "anim_count": 49, "rig_count": 10, "rig_size": 10}}, "us": {"target": "L09", "data": {"rigs": {"/man1/man12us.egg": {"target": "L09.R0002.egg", "data": {"anim_count": 9, "animations": {"/man1/man12us-us10.egg": {"target": "L09.R0002.A0003.egg"}, "/man1/man12us-us7.egg": {"target": "L09.R0002.A0001.egg"}, "/man1/man12us-us4.egg": {"target": "L09.R0002.A0000.egg"}, "/man1/man12us-us9.egg": {"target": "L09.R0002.A0002.egg"}, "/man1/man12us-us5.egg": {"target": "L09.R0002.A0005.egg"}, "/man1/man12us-us3.egg": {"target": "L09.R0002.A0007.egg"}, "/man1/man12us-us2.egg": {"target": "L09.R0002.A0004.egg"}, "/man1/man12us-us6.egg": {"target": "L09.R0002.A0006.egg"}, "/man1/man12us-us8.egg": {"target": "L09.R0002.A0008.egg"}}, "animation_size": 9}}, "/man2/man22us.egg": {"target": "L09.R0007.egg", "data": {"anim_count": 9, "animations": {"/man2/man22us-us2.egg": {"target": "L09.R0007.A0006.egg"}, "/man2/man22us-us7.egg": {"target": "L09.R0007.A0004.egg"}, "/man2/man22us-us10.egg": {"target": "L09.R0007.A0008.egg"}, "/man2/man22us-us3.egg": {"target": "L09.R0007.A0005.egg"}, "/man2/man22us-us4.egg": {"target": "L09.R0007.A0000.egg"}, "/man2/man22us-us5.egg": {"target": "L09.R0007.A0002.egg"}, "/man2/man22us-us8.egg": {"target": "L09.R0007.A0003.egg"}, "/man2/man22us-us9.egg": {"target": "L09.R0007.A0001.egg"}, "/man2/man22us-us6.egg": {"target": "L09.R0007.A0007.egg"}}, "animation_size": 9}}, "/man2/man2us.egg": {"target": "L09.R0008.egg", "data": {"anim_count": 1, "animations": {"/man2/man2us-us.egg": {"target": "L09.R0008.A0000.egg"}}, "animation_size": 1}}, "/man1/man1us.egg": {"target": "L09.R0003.egg", "data": {"anim_count": 1, "animations": {"/man1/man1us-us.egg": {"target": "L09.R0003.A0000.egg"}}, "animation_size": 1}}, "/woman2/woman2us.egg": {"target": "L09.R0001.egg", "data": {"anim_count": 1, "animations": {"/woman2/woman2us-us.egg": {"target": "L09.R0001.A0000.egg"}}, "animation_size": 1}}, "/woman2/women22us.egg": {"target": "L09.R0000.egg", "data": {"anim_count": 9, "animations": {"/woman2/women22us-us7.egg": {"target": "L09.R0000.A0004.egg"}, "/woman2/women22us-us9.egg": {"target": "L09.R0000.A0008.egg"}, "/woman2/women22us-us5.egg": {"target": "L09.R0000.A0000.egg"}, "/woman2/women22us-us3.egg": {"target": "L09.R0000.A0001.egg"}, "/woman2/women22us-us6.egg": {"target": "L09.R0000.A0005.egg"}, "/woman2/women22us-us4.egg": {"target": "L09.R0000.A0003.egg"}, "/woman2/women22us-us8.egg": {"target": "L09.R0000.A0007.egg"}, "/woman2/women22us-us10.egg": {"target": "L09.R0000.A0006.egg"}, "/woman2/women22us-us2.egg": {"target": "L09.R0000.A0002.egg"}}, "animation_size": 9}}, "/woman1/woman12us.egg": {"target": "L09.R0004.egg", "data": {"anim_count": 9, "animations": {"/woman1/woman12us-us10.egg": {"target": "L09.R0004.A0005.egg"}, "/woman1/woman12us-us6.egg": {"target": "L09.R0004.A0003.egg"}, "/woman1/woman12us-us3.egg": {"target": "L09.R0004.A0000.egg"}, "/woman1/woman12us-us8.egg": {"target": "L09.R0004.A0008.egg"}, "/woman1/woman12us-us5.egg": {"target": "L09.R0004.A0007.egg"}, "/woman1/woman12us-us2.egg": {"target": "L09.R0004.A0001.egg"}, "/woman1/woman12us-us9.egg": {"target": "L09.R0004.A0002.egg"}, "/woman1/woman12us-us7.egg": {"target": "L09.R0004.A0006.egg"}, "/woman1/woman12us-us4.egg": {"target": "L09.R0004.A0004.egg"}}, "animation_size": 9}}, "/woman1/woman1us.egg": {"target": "L09.R0005.egg", "data": {"anim_count": 1, "animations": {"/woman1/woman1us-us.egg": {"target": "L09.R0005.A0000.egg"}}, "animation_size": 1}}, "/man0/man0us.egg": {"target": "L09.R0006.egg", "data": {"anim_count": 10, "animations": {"/man0/man0us-us3.egg": {"target": "L09.R0006.A0000.egg"}, "/man0/man0us-us9.egg": {"target": "L09.R0006.A0003.egg"}, "/man0/man0us-us10.egg": {"target": "L09.R0006.A0006.egg"}, "/man0/man0us-us7.egg": {"target": "L09.R0006.A0004.egg"}, "/man0/man0us-us4.egg": {"target": "L09.R0006.A0009.egg"}, "/man0/man0us-us5.egg": {"target": "L09.R0006.A0007.egg"}, "/man0/man0us-us2.egg": {"target": "L09.R0006.A0001.egg"}, "/man0/man0us-us8.egg": {"target": "L09.R0006.A0002.egg"}, "/man0/man0us-us6.egg": {"target": "L09.R0006.A0008.egg"}, "/man0/man0us-us1.egg": {"target": "L09.R0006.A0005.egg"}}, "animation_size": 10}}}, "anim_count": 50, "rig_count": 9, "rig_size": 9}}}, "rig_count": 131}